{"skeleton":{"hash":"Ms5+/qX7R1lh5XPbZ6QsB7B9Jls","spine":"3.7.94","width":2351.13,"height":2103.82,"fps":24,"images":"./images/","audio":"F:/1欧洲/月球/背景/./images"},"bones":[{"name":"root"},{"name":"bone","parent":"root","y":-1007.11,"color":"ff00fcff"},{"name":"ping2_01","parent":"bone","x":-358.78,"y":561.98},{"name":"yyyy","parent":"bone","x":1.75,"y":569.72,"scaleX":1.1},{"name":"zhuan","parent":"yyyy"},{"name":"ping1_04","parent":"bone","length":11.81,"x":118.79,"y":605.68,"color":"76ff00ff"},{"name":"ping1_4","parent":"bone","length":11.81,"x":119.99,"y":600.13,"scaleX":0.752,"color":"76ff00ff"},{"name":"ping1_5","parent":"bone","length":11.81,"x":120.71,"y":593.63,"scaleX":0.558,"color":"76ff00ff"},{"name":"ping1_6","parent":"bone","length":11.81,"x":121.2,"y":587.84,"scaleX":0.999,"color":"76ff00ff"},{"name":"ping1_7","parent":"bone","length":11.81,"x":122.16,"y":582.06,"scaleX":0.758,"color":"76ff00ff"},{"name":"ping1_8","parent":"bone","length":11.81,"x":122.4,"y":575.07,"scaleX":0.882,"color":"76ff00ff"},{"name":"ping1_9","parent":"bone","length":11.81,"x":123.07,"y":568.56,"scaleX":1.014,"color":"76ff00ff"},{"name":"ping1_10","parent":"bone","length":11.81,"x":123.07,"y":563.27,"scaleX":0.621,"color":"76ff00ff"},{"name":"ping1_11","parent":"bone","length":11.81,"x":123.64,"y":556.84,"scaleX":0.893,"color":"76ff00ff"},{"name":"ping1_12","parent":"bone","length":11.81,"x":123.78,"y":550.55,"scaleX":0.516,"color":"76ff00ff"},{"name":"ping1_13","parent":"bone","length":11.81,"x":123.92,"y":543.97,"scaleX":0.817,"color":"76ff00ff"},{"name":"ping2_02","parent":"bone","length":13.81,"rotation":108.95,"x":-418.02,"y":489.01},{"name":"ping2_03","parent":"bone","length":11.66,"rotation":110.56,"x":-413.14,"y":489.59},{"name":"ping2_04","parent":"bone","length":7.83,"rotation":108.89,"x":-407.68,"y":490.18},{"name":"ping2_05","parent":"bone","length":16.65,"rotation":108.44,"x":-402.81,"y":490.76},{"name":"ping2_06","parent":"bone","length":9.56,"rotation":106.59,"x":-398.13,"y":491.15},{"name":"ping2_07","parent":"bone","length":14.06,"rotation":106.93,"x":-392.28,"y":492.52},{"name":"ping2_08","parent":"bone","length":6.41,"rotation":109.54,"x":-387.01,"y":493.1},{"name":"ping2_09","parent":"bone","length":15.11,"rotation":107.27,"x":-381.16,"y":494.08},{"name":"ui_k","parent":"root","color":"ff0000ff"},{"name":"ui01","parent":"ui_k","color":"ff0000ff"},{"name":"ui02","parent":"ui_k","x":1,"y":179,"scaleY":-0.7,"color":"ff0000ff"},{"name":"ui_k2","parent":"root","scaleX":-1,"color":"ff0000ff"},{"name":"ui1","parent":"ui_k2","color":"ff0000ff"},{"name":"ui2","parent":"ui_k2","x":1,"y":179,"scaleY":-0.7,"color":"ff0000ff"},{"name":"bone2","parent":"root","y":-749.05}],"slots":[{"name":"ui31","bone":"bone2"},{"name":"ui14","bone":"ui01","attachment":"ui6"},{"name":"ui20","bone":"ui1","attachment":"ui6"},{"name":"ui25","bone":"ui2","attachment":"ui6"},{"name":"ui16","bone":"ui02","attachment":"ui6"},{"name":"ui15","bone":"ui_k2","attachment":"ui3"},{"name":"ui17","bone":"ui_k2","attachment":"ui3"},{"name":"ui3","bone":"ui_k","attachment":"ui3"},{"name":"ui18","bone":"ui_k2","attachment":"ui3"},{"name":"ui21","bone":"ui1","attachment":"ui1"},{"name":"ui12","bone":"ui_k","attachment":"ui3"},{"name":"ui26","bone":"ui2","attachment":"ui1"},{"name":"ui22","bone":"ui1","attachment":"ui2"},{"name":"ui13","bone":"ui_k","attachment":"ui3"},{"name":"ui27","bone":"ui2","attachment":"ui2"},{"name":"ui23","bone":"ui1","attachment":"ui5"},{"name":"ui1","bone":"ui01","attachment":"ui1"},{"name":"ui24","bone":"ui1","attachment":"ui5"},{"name":"ui28","bone":"ui2","attachment":"ui5"},{"name":"ui5","bone":"ui02","attachment":"ui1"},{"name":"ui29","bone":"ui2","attachment":"ui5"},{"name":"ui30","bone":"ui2","attachment":"ui5"},{"name":"ui2","bone":"ui01","attachment":"ui2"},{"name":"ui19","bone":"bone"},{"name":"ui6","bone":"ui02","attachment":"ui2"},{"name":"ui7","bone":"ui01","attachment":"ui5"},{"name":"ui11","bone":"ui01","attachment":"ui5"},{"name":"ui8","bone":"ui02","attachment":"ui5"},{"name":"ui9","bone":"ui02","attachment":"ui5"},{"name":"ui10","bone":"ui02","attachment":"ui5"},{"name":"ui4","bone":"bone"},{"name":"ping3_03","bone":"bone"},{"name":"ping3_02","bone":"bone"},{"name":"ping3_01","bone":"bone"},{"name":"baidi0","bone":"bone","color":"4aff00ff"},{"name":"baidi1","bone":"bone","color":"4aff00ff"},{"name":"baidi2","bone":"bone","color":"4aff00ff"},{"name":"baidi3","bone":"bone","color":"4aff00ff"},{"name":"ping2_10","bone":"bone"},{"name":"ping2_09","bone":"ping2_09"},{"name":"ping2_08","bone":"ping2_08"},{"name":"ping2_07","bone":"ping2_07"},{"name":"ping2_06","bone":"ping2_06"},{"name":"ping2_05","bone":"ping2_05"},{"name":"ping2_04","bone":"ping2_04"},{"name":"ping2_03","bone":"ping2_03"},{"name":"ping2_02","bone":"ping2_02"},{"name":"ping2_01","bone":"ping2_01"},{"name":"ping1_07","bone":"bone"},{"name":"ping1_06","bone":"bone"},{"name":"ping1_05","bone":"bone"},{"name":"ping1_04","bone":"ping1_04"},{"name":"ping1_5","bone":"ping1_4"},{"name":"ping1_6","bone":"ping1_5"},{"name":"ping1_7","bone":"ping1_6"},{"name":"ping1_8","bone":"ping1_7"},{"name":"ping1_9","bone":"ping1_8"},{"name":"ping1_10","bone":"ping1_9"},{"name":"ping1_11","bone":"ping1_10"},{"name":"ping1_12","bone":"ping1_11"},{"name":"ping1_13","bone":"ping1_12"},{"name":"ping1_14","bone":"ping1_13"},{"name":"ping1_03","bone":"bone"},{"name":"ping1_02","bone":"zhuan"},{"name":"ping1_01","bone":"yyyy"},{"name":"ping1_1","bone":"yyyy"},{"name":"ping_g","bone":"bone","blend":"additive"}],"skins":{"default":{"baidi0":{"baidi0":{"x":-278.4,"y":521.62,"scaleX":1.227,"scaleY":0.675,"rotation":13.5,"width":13,"height":13}},"baidi1":{"baidi0":{"x":-280.73,"y":530.59,"scaleX":1.227,"scaleY":0.675,"rotation":13.5,"width":13,"height":13}},"baidi2":{"baidi0":{"x":-283.3,"y":539.78,"scaleX":1.227,"scaleY":0.675,"rotation":13.5,"width":13,"height":13}},"baidi3":{"baidi0":{"x":-285.56,"y":549.03,"scaleX":1.227,"scaleY":0.675,"rotation":13.5,"width":13,"height":13}},"ping1_01":{"ping1_01":{"x":-48.49,"y":-23.52,"width":13,"height":13}},"ping1_02":{"ping1_02":{"x":35.02,"y":35.42,"width":70,"height":71}},"ping1_03":{"ping1_03":{"x":1.91,"y":569.21,"width":158,"height":141}},"ping1_04":{"ping1_04":{"x":21.13,"y":-0.47,"width":44,"height":5}},"ping1_05":{"ping1_05":{"x":114.41,"y":574.21,"width":9,"height":67}},"ping1_06":{"ping1_06":{"x":-107.59,"y":620.71,"width":87,"height":28}},"ping1_07":{"ping1_07":{"x":-126.59,"y":534.71,"width":67,"height":42}},"ping1_1":{"ping1_01":{"x":54.55,"y":44.19,"scaleX":1.2,"scaleY":1.2,"width":13,"height":13}},"ping1_10":{"ping1_04":{"x":21.13,"y":-0.47,"width":44,"height":5}},"ping1_11":{"ping1_04":{"x":21.13,"y":-0.47,"width":44,"height":5}},"ping1_12":{"ping1_04":{"x":21.13,"y":-0.47,"width":44,"height":5}},"ping1_13":{"ping1_04":{"x":21.13,"y":-0.47,"width":44,"height":5}},"ping1_14":{"ping1_04":{"x":21.13,"y":-0.47,"width":44,"height":5}},"ping1_5":{"ping1_04":{"x":21.13,"y":-0.47,"width":44,"height":5}},"ping1_6":{"ping1_04":{"x":21.13,"y":-0.47,"width":44,"height":5}},"ping1_7":{"ping1_04":{"x":21.13,"y":-0.47,"width":44,"height":5}},"ping1_8":{"ping1_04":{"x":21.13,"y":-0.47,"width":44,"height":5}},"ping1_9":{"ping1_04":{"x":21.13,"y":-0.47,"width":44,"height":5}},"ping2_01":{"ping2_01":{"x":-2.31,"y":-0.28,"width":90,"height":78}},"ping2_02":{"ping2_02":{"x":14.91,"y":-0.29,"rotation":-108.95,"width":13,"height":31}},"ping2_03":{"ping2_03":{"x":10.21,"y":-0.15,"rotation":-110.56,"width":11,"height":21}},"ping2_04":{"ping2_04":{"x":7.27,"y":-0.47,"rotation":-108.89,"width":9,"height":17}},"ping2_05":{"ping2_05":{"x":15.69,"y":-0.19,"rotation":-108.44,"width":15,"height":32}},"ping2_06":{"ping2_06":{"x":7.32,"y":-0.13,"rotation":-106.59,"width":8,"height":15}},"ping2_07":{"ping2_07":{"x":12.62,"y":-0.38,"rotation":-106.93,"width":13,"height":26}},"ping2_08":{"ping2_08":{"x":4.39,"y":0.11,"rotation":-109.54,"width":7,"height":11}},"ping2_09":{"ping2_09":{"x":10.69,"y":0.27,"rotation":-107.27,"width":11,"height":23}},"ping2_10":{"ping2_10":{"x":-290.59,"y":561.21,"width":47,"height":97}},"ping3_01":{"ping3_01":{"x":312.41,"y":536.21,"width":79,"height":55}},"ping3_02":{"ping3_02":{"x":330.91,"y":593.71,"width":80,"height":34}},"ping3_03":{"ping3_03":{"x":399.91,"y":548.71,"width":96,"height":110}},"ping_g":{"ping_g":{"y":534.58,"scaleX":4,"scaleY":4,"width":209,"height":120}},"ui1":{"ui1":{"x":-760.19,"y":-685.5,"width":484,"height":629}},"ui10":{"ui5":{"x":-578.88,"y":-1179.39,"width":113,"height":139}},"ui11":{"ui5":{"x":-578.88,"y":-981.09,"width":113,"height":139}},"ui12":{"ui3":{"x":-615.96,"y":313.98,"scaleX":0.953,"scaleY":-0.95,"rotation":-3.32,"width":121,"height":493}},"ui13":{"ui3":{"x":-922,"y":113.05,"rotation":-106.33,"width":121,"height":493}},"ui14":{"ui6":{"x":-437.39,"y":-161.13,"scaleX":2,"scaleY":2,"width":224,"height":219}},"ui15":{"ui3":{"x":-627.14,"y":-155.76,"width":121,"height":493}},"ui16":{"ui6":{"x":-432.19,"y":-172.31,"scaleX":2,"scaleY":2,"width":224,"height":219}},"ui17":{"ui3":{"x":-615.96,"y":313.98,"scaleX":0.953,"scaleY":-0.95,"rotation":-3.32,"width":121,"height":493}},"ui18":{"ui3":{"x":-922,"y":113.05,"rotation":-106.33,"width":121,"height":493}},"ui19":{"ui4":{"x":282,"y":340.48,"scaleY":-1,"rotation":180,"width":570,"height":682}},"ui2":{"ui2":{"x":-260.38,"y":-427.2,"width":520,"height":144}},"ui20":{"ui6":{"x":-437.39,"y":-161.13,"scaleX":2,"scaleY":2,"width":224,"height":219}},"ui21":{"ui1":{"x":-760.19,"y":-685.5,"width":484,"height":629}},"ui22":{"ui2":{"x":-260.38,"y":-427.2,"width":520,"height":144}},"ui23":{"ui5":{"x":-578.88,"y":-927.7,"width":113,"height":139}},"ui24":{"ui5":{"x":-578.88,"y":-981.09,"width":113,"height":139}},"ui25":{"ui6":{"x":-432.19,"y":-172.31,"scaleX":2,"scaleY":2,"width":224,"height":219}},"ui26":{"ui1":{"x":-760.19,"y":-685.71,"width":484,"height":629}},"ui27":{"ui2":{"x":-260.38,"y":-427.2,"width":520,"height":144}},"ui28":{"ui5":{"x":-578.88,"y":-927.7,"width":113,"height":139}},"ui29":{"ui5":{"x":-578.88,"y":-1057.72,"width":113,"height":139}},"ui3":{"ui3":{"x":-627.14,"y":-155.76,"width":121,"height":493}},"ui30":{"ui5":{"x":-578.88,"y":-1179.39,"width":113,"height":139}},"ui31":{"ui8":{"x":0.5,"y":35.61,"scaleX":29.606,"scaleY":1.827,"width":41,"height":369}},"ui4":{"ui4":{"x":-282,"y":340.48,"width":570,"height":682}},"ui5":{"ui1":{"x":-760.19,"y":-685.71,"width":484,"height":629}},"ui6":{"ui2":{"x":-260.38,"y":-427.2,"width":520,"height":144}},"ui7":{"ui5":{"x":-578.88,"y":-927.7,"width":113,"height":139}},"ui8":{"ui5":{"x":-578.88,"y":-927.7,"width":113,"height":139}},"ui9":{"ui5":{"x":-578.88,"y":-1057.72,"width":113,"height":139}}}},"animations":{"cabin":{"slots":{"baidi0":{"color":[{"time":0,"color":"49ff0000"},{"time":0.0833,"color":"49ff00ff","curve":"stepped"},{"time":1.6667,"color":"49ff00ff"},{"time":1.7917,"color":"49ff0000"}],"attachment":[{"time":0,"name":"baidi0"}]},"baidi1":{"color":[{"time":0,"color":"49ff0000","curve":"stepped"},{"time":0.4167,"color":"49ff0000"},{"time":0.5,"color":"49ff00ff","curve":"stepped"},{"time":1.6667,"color":"49ff00ff"},{"time":1.7917,"color":"49ff0000"}],"attachment":[{"time":0,"name":"baidi0"}]},"baidi2":{"color":[{"time":0,"color":"49ff0000","curve":"stepped"},{"time":0.8333,"color":"49ff0000"},{"time":0.9167,"color":"49ff00ff","curve":"stepped"},{"time":1.6667,"color":"49ff00ff"},{"time":1.7917,"color":"49ff0000"}],"attachment":[{"time":0,"name":"baidi0"}]},"baidi3":{"color":[{"time":0,"color":"49ff0000","curve":"stepped"},{"time":1.25,"color":"49ff0000"},{"time":1.3333,"color":"49ff00ff","curve":"stepped"},{"time":1.6667,"color":"49ff00ff"},{"time":1.7917,"color":"49ff0000"}],"attachment":[{"time":0,"name":"baidi0"}]},"ping1_01":{"color":[{"time":0.875,"color":"ffffff00"},{"time":1,"color":"ffffffff","curve":"stepped"},{"time":1.2917,"color":"ffffffff"},{"time":1.4167,"color":"ffffff00"}],"attachment":[{"time":0,"name":"ping1_01"},{"time":1.4167,"name":null}]},"ping1_1":{"color":[{"time":0.1667,"color":"ffffffff"},{"time":0.2917,"color":"ffffff00","curve":"stepped"},{"time":1.7917,"color":"ffffff00"},{"time":1.9167,"color":"ffffffff"}],"attachment":[{"time":1.7917,"name":"ping1_01"}]},"ping1_02":{"attachment":[{"time":0,"name":"ping1_02"}]},"ping1_03":{"attachment":[{"time":0,"name":"ping1_03"}]},"ping1_04":{"attachment":[{"time":0,"name":"ping1_04"}]},"ping1_5":{"attachment":[{"time":0,"name":"ping1_04"}]},"ping1_05":{"attachment":[{"time":0,"name":"ping1_05"}]},"ping1_6":{"attachment":[{"time":0,"name":"ping1_04"}]},"ping1_06":{"color":[{"time":0,"color":"ffffffff"},{"time":0.125,"color":"2bff00ff","curve":"stepped"},{"time":0.5,"color":"2bff00ff"},{"time":0.625,"color":"ffffffff","curve":"stepped"},{"time":1,"color":"ffffffff"},{"time":1.125,"color":"2bff00ff","curve":"stepped"},{"time":1.5,"color":"2bff00ff"},{"time":1.625,"color":"ffffffff"}],"attachment":[{"time":0,"name":"ping1_06"}]},"ping1_7":{"attachment":[{"time":0,"name":"ping1_04"}]},"ping1_07":{"attachment":[{"time":0,"name":"ping1_07"}]},"ping1_8":{"attachment":[{"time":0,"name":"ping1_04"}]},"ping1_9":{"attachment":[{"time":0,"name":"ping1_04"}]},"ping1_10":{"attachment":[{"time":0,"name":"ping1_04"}]},"ping1_11":{"attachment":[{"time":0,"name":"ping1_04"}]},"ping1_12":{"attachment":[{"time":0,"name":"ping1_04"}]},"ping1_13":{"attachment":[{"time":0,"name":"ping1_04"}]},"ping1_14":{"attachment":[{"time":0,"name":"ping1_04"}]},"ping2_01":{"attachment":[{"time":0,"name":"ping2_01"}]},"ping2_02":{"attachment":[{"time":0,"name":"ping2_02"}]},"ping2_03":{"attachment":[{"time":0,"name":"ping2_03"}]},"ping2_04":{"attachment":[{"time":0,"name":"ping2_04"}]},"ping2_05":{"attachment":[{"time":0,"name":"ping2_05"}]},"ping2_06":{"attachment":[{"time":0,"name":"ping2_06"}]},"ping2_07":{"attachment":[{"time":0,"name":"ping2_07"}]},"ping2_08":{"attachment":[{"time":0,"name":"ping2_08"}]},"ping2_09":{"attachment":[{"time":0,"name":"ping2_09"}]},"ping2_10":{"attachment":[{"time":0,"name":"ping2_10"}]},"ping3_01":{"attachment":[{"time":0,"name":"ping3_01"}]},"ping3_02":{"color":[{"time":0,"color":"ffffffff"},{"time":0.125,"color":"2bff00ff","curve":"stepped"},{"time":0.5,"color":"2bff00ff"},{"time":0.625,"color":"ffffffff","curve":"stepped"},{"time":1,"color":"ffffffff"},{"time":1.125,"color":"2bff00ff","curve":"stepped"},{"time":1.5,"color":"2bff00ff"},{"time":1.625,"color":"ffffffff"}],"attachment":[{"time":0,"name":"ping3_02"}]},"ping3_03":{"attachment":[{"time":0,"name":"ping3_03"}]},"ping_g":{"color":[{"time":0,"color":"ffffffff"},{"time":0.5,"color":"ffffff77"},{"time":1,"color":"ffffffff"},{"time":1.5,"color":"ffffff77"},{"time":2,"color":"ffffffff"}],"attachment":[{"time":0,"name":"ping_g"}]},"ui4":{"attachment":[{"time":0,"name":"ui4"}]},"ui19":{"attachment":[{"time":0,"name":"ui4"}]}},"bones":{"zhuan":{"rotate":[{"time":0,"angle":0},{"time":1,"angle":-180},{"time":2,"angle":1.1}]},"ping1_04":{"scale":[{"time":0,"x":1,"y":1,"curve":[0.25,0,0.75,1]},{"time":0.4167,"x":0.653,"y":1,"curve":[0.25,0,0.75,1]},{"time":0.8333,"x":0.788,"y":1,"curve":[0.25,0,0.75,1]},{"time":1.25,"x":0.616,"y":1.136,"curve":[0.25,0,0.75,1]},{"time":1.875,"x":1,"y":1}]},"ping1_7":{"scale":[{"time":0.125,"x":1,"y":1,"curve":[0.25,0,0.75,1]},{"time":0.7083,"x":0.653,"y":1,"curve":[0.25,0,0.75,1]},{"time":1.125,"x":0.788,"y":1,"curve":[0.25,0,0.75,1]},{"time":1.5417,"x":0.616,"y":1.136,"curve":[0.25,0,0.75,1]},{"time":2,"x":1,"y":1}]},"ping1_9":{"scale":[{"time":0,"x":0.722,"y":1,"curve":[0.25,0,0.75,1]},{"time":0.5833,"x":1,"y":1,"curve":[0.25,0,0.75,1]},{"time":1.0417,"x":0.833,"y":1,"curve":[0.25,0,0.75,1]},{"time":1.4583,"x":0.965,"y":1,"curve":[0.25,0,0.75,1]},{"time":2,"x":0.722,"y":1}]},"ping1_11":{"scale":[{"time":0,"x":0.722,"y":1,"curve":[0.25,0,0.75,1]},{"time":0.4167,"x":1,"y":1,"curve":[0.25,0,0.75,1]},{"time":0.875,"x":0.833,"y":1,"curve":[0.25,0,0.75,1]},{"time":1.2917,"x":0.965,"y":1,"curve":[0.25,0,0.75,1]},{"time":2,"x":0.722,"y":1}]},"ping1_4":{"scale":[{"time":0,"x":0.616,"y":1.136,"curve":[0.25,0,0.75,1]},{"time":0.75,"x":1,"y":1,"curve":[0.25,0,0.75,1]},{"time":1.1667,"x":0.653,"y":1,"curve":[0.25,0,0.75,1]},{"time":1.5833,"x":0.788,"y":1,"curve":[0.25,0,0.75,1]},{"time":2,"x":0.616,"y":1.136}]},"ping1_5":{"scale":[{"time":0,"x":1,"y":1,"curve":[0.25,0,0.75,1]},{"time":0.5417,"x":0.653,"y":1,"curve":[0.25,0,0.75,1]},{"time":0.9583,"x":0.788,"y":1,"curve":[0.25,0,0.75,1]},{"time":1.375,"x":0.616,"y":1.136,"curve":[0.25,0,0.75,1]},{"time":2,"x":1,"y":1}]},"ping1_6":{"scale":[{"time":0,"x":0.722,"y":1,"curve":[0.25,0,0.75,1]},{"time":0.6667,"x":1,"y":1,"curve":[0.25,0,0.75,1]},{"time":1.125,"x":0.833,"y":1,"curve":[0.25,0,0.75,1]},{"time":1.5417,"x":0.965,"y":1,"curve":[0.25,0,0.75,1]},{"time":2,"x":0.722,"y":1}]},"ping1_8":{"scale":[{"time":0,"x":1,"y":1,"curve":[0.25,0,0.75,1]},{"time":0.5,"x":0.869,"y":1,"curve":[0.25,0,0.75,1]},{"time":1,"x":1,"y":1,"curve":[0.25,0,0.75,1]},{"time":1.5,"x":0.869,"y":1,"curve":[0.25,0,0.75,1]},{"time":2,"x":1,"y":1}]},"ping1_10":{"scale":[{"time":0,"x":1,"y":1,"curve":[0.25,0,0.75,1]},{"time":0.5,"x":0.729,"y":1,"curve":[0.25,0,0.75,1]},{"time":1,"x":1.138,"y":1,"curve":[0.25,0,0.75,1]},{"time":1.5,"x":0.937,"y":1,"curve":[0.25,0,0.75,1]},{"time":2,"x":1,"y":1}]},"ping1_12":{"scale":[{"time":0.125,"x":1,"y":1,"curve":[0.25,0,0.75,1]},{"time":0.7083,"x":0.653,"y":1,"curve":[0.25,0,0.75,1]},{"time":1.125,"x":0.788,"y":1,"curve":[0.25,0,0.75,1]},{"time":1.5417,"x":0.616,"y":1.136,"curve":[0.25,0,0.75,1]},{"time":2,"x":1,"y":1}]},"ping1_13":{"scale":[{"time":0,"x":0.946,"y":1.136,"curve":[0.25,0,0.75,1]},{"time":0.3333,"x":0.854,"y":1,"curve":[0.25,0,0.75,1]},{"time":0.7083,"x":0.962,"y":1,"curve":[0.25,0,0.75,1]},{"time":1.1667,"x":0.653,"y":1,"curve":[0.25,0,0.75,1]},{"time":1.5833,"x":0.788,"y":1,"curve":[0.25,0,0.75,1]},{"time":2,"x":0.946,"y":1.136}]},"ping2_01":{"rotate":[{"time":0,"angle":0,"curve":[0.375,0.5,0.75,1]},{"time":0.5,"angle":6,"curve":[0.25,0,0.75,1]},{"time":1.5,"angle":-6,"curve":[0.25,0,0.625,0.5]},{"time":2,"angle":0}],"translate":[{"time":0,"x":-2.44,"y":2.44,"curve":[0.25,0,0.75,1]},{"time":1,"x":1.22,"y":-6.1,"curve":[0.25,0,0.75,1]},{"time":2,"x":-2.44,"y":2.44}]},"ping2_02":{"scale":[{"time":0,"x":1,"y":1,"curve":[0.25,0,0.75,1]},{"time":0.5,"x":0.823,"y":1,"curve":[0.25,0,0.75,1]},{"time":1,"x":1,"y":1,"curve":[0.25,0,0.75,1]},{"time":1.5,"x":0.823,"y":1,"curve":[0.25,0,0.75,1]},{"time":2,"x":1,"y":1}]},"ping2_05":{"scale":[{"time":0,"x":0.967,"y":1,"curve":[0.379,0.6,0.724,1]},{"time":0.125,"x":1,"y":1,"curve":[0.25,0,0.75,1]},{"time":0.625,"x":0.823,"y":1,"curve":[0.25,0,0.75,1]},{"time":1.125,"x":1.088,"y":1,"curve":[0.25,0,0.75,1]},{"time":1.625,"x":0.823,"y":1,"curve":[0.242,0,0.667,0.67]},{"time":2,"x":0.967,"y":1}]},"ping2_07":{"scale":[{"time":0,"x":0.911,"y":1,"curve":[0.375,0.5,0.75,1]},{"time":0.25,"x":1,"y":1,"curve":[0.25,0,0.75,1]},{"time":0.75,"x":0.715,"y":1,"curve":[0.25,0,0.75,1]},{"time":1.25,"x":1,"y":1,"curve":[0.25,0,0.75,1]},{"time":1.75,"x":0.823,"y":1,"curve":[0.25,0,0.625,0.5]},{"time":2,"x":0.911,"y":1}]},"ping2_03":{"scale":[{"time":0,"x":1,"y":1,"curve":[0.25,0,0.75,1]},{"time":0.4167,"x":0.751,"y":1,"curve":[0.25,0,0.75,1]},{"time":0.8333,"x":1.203,"y":1,"curve":[0.25,0,0.75,1]},{"time":1.4583,"x":0.857,"y":1,"curve":[0.25,0,0.75,1]},{"time":2,"x":1,"y":1}]},"ping2_08":{"scale":[{"time":0,"x":1.5,"y":1,"curve":[0.25,0,0.75,1]},{"time":0.7083,"x":0.751,"y":1,"curve":[0.25,0,0.75,1]},{"time":1.125,"x":1.203,"y":1,"curve":[0.25,0,0.75,1]},{"time":1.5833,"x":0.718,"y":1,"curve":[0.25,0,0.75,1]},{"time":2,"x":1.5,"y":1}]},"ping2_09":{"scale":[{"time":0,"x":1,"y":1,"curve":[0.25,0,0.75,1]},{"time":0.4583,"x":1.321,"y":1,"curve":[0.25,0,0.75,1]},{"time":0.9167,"x":0.934,"y":1,"curve":[0.25,0,0.75,1]},{"time":1.375,"x":1.134,"y":1,"curve":[0.25,0,0.75,1]},{"time":1.875,"x":1,"y":1}]},"ping2_04":{"scale":[{"time":0.125,"x":1,"y":1,"curve":[0.25,0,0.75,1]},{"time":0.7083,"x":1.321,"y":1,"curve":[0.25,0,0.75,1]},{"time":1.125,"x":0.934,"y":1,"curve":[0.25,0,0.75,1]},{"time":1.5833,"x":1.134,"y":1,"curve":[0.25,0,0.75,1]},{"time":2,"x":1,"y":1}]},"ping2_06":{"scale":[{"time":0,"x":1.5,"y":1,"curve":[0.25,0,0.75,1]},{"time":0.375,"x":0.751,"y":1,"curve":[0.25,0,0.75,1]},{"time":0.7917,"x":1.203,"y":1,"curve":[0.25,0,0.75,1]},{"time":1.25,"x":0.718,"y":1,"curve":[0.25,0,0.75,1]},{"time":2,"x":1.5,"y":1}]}}},"cabin_s":{"slots":{"ui31":{"color":[{"time":0,"color":"ffffff9f"}],"attachment":[{"time":0,"name":"ui8"}]}}}}}